{
    "Dark": {
        "background-blur": "#33000000",
        "background-inverse": "#f3f4f4",
        "border-disabled": "#494a4d",
        "border-interactive": "#fb6361",
        "border-strong": "#616366",
        "border-strong-selected": "#f4f4f5",
        "border-subtle": "#303233",
        "border-subtle-selected": "#f4f4f5",
        "button-brand": "#f23433",
        "button-brand-hover": "#fb6361",
        "button-brand-pressed": "#fd9997",
        "button-disabled": "#1affffff",
        "button-error": "#f63d6b",
        "button-error-hover": "#fd6f90",
        "button-error-pressed": "#fea3b5",
        "button-outline": "#f4f4f5",
        "button-outline-background-hover": "#0dffffff",
        "button-outline-hover": "#a3a6ad",
        "button-outline-pressed": "#bdc0c4",
        "button-primary": "#f4f4f5",
        "button-primary-hover": "#a3a6ad",
        "button-primary-pressed": "#bdc0c4",
        "button-secondary": "#494a4d",
        "button-secondary-hover": "#616366",
        "button-secondary-pressed": "#797c80",
        "focus": "#2647d0",
        "icon-accent": "#fafafb",
        "icon-disabled": "#797c80",
        "icon-inverse": "#303233",
        "icon-inverse-accent": "#04101e",
        "icon-on-color": "#fafafa",
        "icon-on-color-disabled": "#919397",
        "icon-primary": "#f3f4f4",
        "icon-secondary": "#a9abad",
        "indicator-blue": "#31d0fe",
        "indicator-green": "#29dd74",
        "indicator-indigo": "#69a3fb",
        "indicator-magenta": "#f4a8e3",
        "indicator-orange": "#feb273",
        "indicator-pink": "#fd6f90",
        "indicator-yellow": "#fdc121",
        "interactive": "#fb6361",
        "link-inverse": "#2c5beb",
        "link-primary": "#69a3fb",
        "link-visited": "#d9e8ff",
        "notification-error": "#891240",
        "notification-info": "#085371",
        "notification-success": "#01532b",
        "notification-warning": "#94410b",
        "page-background": "#18191a",
        "selection-control": "#f4f4f5",
        "support-error": "#fd6f90",
        "support-info": "#0096c9",
        "support-success": "#09bf5b",
        "support-warning": "#f7a308",
        "surface-1": "#303233",
        "surface-2": "#494a4d",
        "surface-3": "#616366",
        "text-accent": "#fafafb",
        "text-disabled": "#797c80",
        "text-error": "#fd6f90",
        "text-info": "#05baf1",
        "text-inverse": "#303233",
        "text-inverse-accent": "#04101e",
        "text-on-color": "#fafafa",
        "text-on-color-disabled": "#919397",
        "text-placeholder": "#c1c2c4",
        "text-primary": "#f3f4f4",
        "text-secondary": "#a9abad",
        "text-success": "#09bf5b",
        "text-warning": "#f7a308",
        "toast-background": "#c1c2c4"
    },
    "Light": {
        "background-blur": "#33000000",
        "background-inverse": "#494a4d",
        "border-disabled": "#d8d9db",
        "border-interactive": "#dd1405",
        "border-strong": "#d8d9db",
        "border-strong-selected": "#04101e",
        "border-subtle": "#f3f4f4",
        "border-subtle-selected": "#04101e",
        "button-brand": "#dd1405",
        "button-brand-hover": "#b61714",
        "button-brand-pressed": "#931715",
        "button-disabled": "#1a000000",
        "button-error": "#e31b57",
        "button-error-hover": "#c0104a",
        "button-error-pressed": "#a11045",
        "button-outline": "#04101e",
        "button-outline-background-hover": "#0d000000",
        "button-outline-hover": "#39424e",
        "button-outline-pressed": "#535b65",
        "button-primary": "#04101e",
        "button-primary-hover": "#39424e",
        "button-primary-pressed": "#535b65",
        "button-secondary": "#f3f4f4",
        "button-secondary-hover": "#d8d9db",
        "button-secondary-pressed": "#c1c2c4",
        "focus": "#bdd9ff",
        "icon-accent": "#04101e",
        "icon-disabled": "#c1c2c4",
        "icon-inverse": "#fafafa",
        "icon-inverse-accent": "#fafafb",
        "icon-on-color": "#fafafa",
        "icon-on-color-disabled": "#a9abad",
        "icon-primary": "#303233",
        "icon-secondary": "#616366",
        "indicator-blue": "#05baf1",
        "indicator-green": "#09bf5b",
        "indicator-indigo": "#477ef7",
        "indicator-magenta": "#e248c2",
        "indicator-orange": "#fb6514",
        "indicator-pink": "#f63d6b",
        "indicator-yellow": "#f7a308",
        "interactive": "#dd1405",
        "link-inverse": "#69a3fb",
        "link-primary": "#2c5beb",
        "link-visited": "#233783",
        "notification-error": "#ffe4e8",
        "notification-info": "#dff4fe",
        "notification-success": "#cffcdb",
        "notification-warning": "#fef4c6",
        "page-background": "#ffffff",
        "selection-control": "#04101e",
        "support-error": "#e31b57",
        "support-info": "#05baf1",
        "support-success": "#009b48",
        "support-warning": "#f7a308",
        "surface-1": "#fafafa",
        "surface-2": "#f3f4f4",
        "surface-3": "#d8d9db",
        "text-accent": "#04101e",
        "text-disabled": "#c1c2c4",
        "text-error": "#e31b57",
        "text-info": "#0078a4",
        "text-inverse": "#fafafa",
        "text-inverse-accent": "#fafafb",
        "text-on-color": "#fafafa",
        "text-on-color-disabled": "#a9abad",
        "text-placeholder": "#616366",
        "text-primary": "#303233",
        "text-secondary": "#616366",
        "text-success": "#007c3e",
        "text-warning": "#b55407",
        "toast-background": "#494a4d"
    }
}
