{
    "Dark": {
        "background-blur": "#80000000",
        "background-inverse": "#ffefeff0",
        "border-brand": "#fff23433",
        "border-disabled": "#ff494a4d",
        "border-strong": "#ff535455",
        "border-strong-selected": "#fff4f4f5",
        "border-subtle": "#ff252626",
        "border-subtle-selected": "#fff4f4f5",
        "brand-container-default": "#4df23433",
        "brand-container-hover": "#66f23433",
        "brand-container-pressed": "#80f23433",
        "brand-default": "#fff23433",
        "brand-hover": "#fffb6361",
        "brand-on-brand": "#fff7f7f7",
        "brand-on-container": "#fffcefef",
        "brand-pressed": "#fffd9997",
        "button-brand": "#fff23433",
        "button-brand-hover": "#fffb6361",
        "button-brand-pressed": "#fffd9997",
        "button-disabled": "#ff2c2d2d",
        "button-error": "#fff63d6b",
        "button-error-hover": "#fffd6f90",
        "button-error-pressed": "#fffea3b5",
        "button-outline": "#fff4f4f5",
        "button-outline-background-hover": "#0dffffff",
        "button-outline-hover": "#ffa3a6ad",
        "button-outline-pressed": "#ffbdc0c4",
        "button-primary": "#fff4f4f5",
        "button-primary-hover": "#ffa3a6ad",
        "button-primary-pressed": "#ffbdc0c4",
        "button-secondary": "#33989a9c",
        "button-secondary-hover": "#4d989a9c",
        "button-secondary-pressed": "#66989a9c",
        "components-interactive": "#fff23433",
        "focus-color": "#ff2647d0",
        "icon-accent": "#fffafafb",
        "icon-brand": "#fff23433",
        "icon-disabled": "#ff797c80",
        "icon-inverse": "#ff303233",
        "icon-inverse-accent": "#ff04101e",
        "icon-inverse-secondary": "#ff616366",
        "icon-on-color": "#fffafafa",
        "icon-on-color-disabled": "#ff919397",
        "icon-primary": "#fff3f4f4",
        "icon-secondary": "#ffa9abad",
        "indicator-blue": "#ff31d0fe",
        "indicator-green": "#ff29dd74",
        "indicator-indigo": "#ff69a3fb",
        "indicator-magenta": "#fff4a8e3",
        "indicator-orange": "#fffeb273",
        "indicator-pink": "#fffd6f90",
        "indicator-yellow": "#fffdc121",
        "link-inverse": "#ff2c5beb",
        "link-primary": "#ff69a3fb",
        "link-visited": "#ffd9e8ff",
        "neutral-container-default": "#33989a9c",
        "neutral-container-hover": "#4d989a9c",
        "neutral-container-pressed": "#66989a9c",
        "neutral-default": "#ffb0b1b3",
        "neutral-hover": "#ffd7d8d9",
        "neutral-on-container": "#ffb0b1b3",
        "neutral-on-grey": "#ff222324",
        "neutral-pressed": "#ffefeff0",
        "notification-error": "#ff891240",
        "notification-info": "#ff085371",
        "notification-success": "#ff01532b",
        "notification-warning": "#ff94410b",
        "page-background": "#ff151616",
        "selection-control": "#fff4f4f5",
        "selection-control-alt": "#ff6e747d",
        "support-error": "#fffd6f90",
        "support-info": "#ff0096c9",
        "support-success": "#ff09bf5b",
        "support-warning": "#fff7a308",
        "surface-1": "#ff222324",
        "surface-2": "#ff2a2b2c",
        "surface-3": "#ff3a3b3d",
        "surface-inverse-accent": "#ffbdc0c4",
        "surface-transparent": "#b3000000",
        "text-accent": "#fffafafb",
        "text-brand": "#fff23433",
        "text-disabled": "#ff797c80",
        "text-error": "#fffd6f90",
        "text-info": "#ff05baf1",
        "text-inverse": "#ff303233",
        "text-inverse-accent": "#ff04101e",
        "text-inverse-secondary": "#ff616366",
        "text-on-color": "#fffafafa",
        "text-on-color-disabled": "#ff919397",
        "text-placeholder": "#ffc1c2c4",
        "text-primary": "#fff3f4f4",
        "text-secondary": "#ffa9abad",
        "text-success": "#ff09bf5b",
        "text-warning": "#fff7a308",
        "toast-background": "#ffc1c2c4"
    },
    "Light": {
        "background-blur": "#33000000",
        "background-inverse": "#ff2a2b2c",
        "border-brand": "#ffdd1405",
        "border-disabled": "#ffd8d9db",
        "border-strong": "#ffdcdddd",
        "border-strong-selected": "#ff04101e",
        "border-subtle": "#fff6f6f7",
        "border-subtle-selected": "#ff04101e",
        "brand-container-default": "#1add1405",
        "brand-container-hover": "#33dd1405",
        "brand-container-pressed": "#4ddd1405",
        "brand-default": "#ffdd1405",
        "brand-hover": "#ffb61714",
        "brand-on-brand": "#fff7f7f7",
        "brand-on-container": "#ff7b2118",
        "brand-pressed": "#ff931715",
        "button-brand": "#ffdd1405",
        "button-brand-hover": "#ffb61714",
        "button-brand-pressed": "#ff931715",
        "button-disabled": "#ffe5e5e5",
        "button-error": "#ffe31b57",
        "button-error-hover": "#ffc0104a",
        "button-error-pressed": "#ffa11045",
        "button-outline": "#ff04101e",
        "button-outline-background-hover": "#0d000000",
        "button-outline-hover": "#ff39424e",
        "button-outline-pressed": "#ff535b65",
        "button-primary": "#ff04101e",
        "button-primary-hover": "#ff39424e",
        "button-primary-pressed": "#ff535b65",
        "button-secondary": "#1a616366",
        "button-secondary-hover": "#33616366",
        "button-secondary-pressed": "#4d616366",
        "components-interactive": "#ffdd1405",
        "focus-color": "#ffbdd9ff",
        "icon-accent": "#ff04101e",
        "icon-brand": "#ffdd1405",
        "icon-disabled": "#ffc1c2c4",
        "icon-inverse": "#fffafafa",
        "icon-inverse-accent": "#fffafafb",
        "icon-inverse-secondary": "#ffb0b1b3",
        "icon-on-color": "#fffafafa",
        "icon-on-color-disabled": "#ffa9abad",
        "icon-primary": "#ff303233",
        "icon-secondary": "#ff616366",
        "indicator-blue": "#ff05baf1",
        "indicator-green": "#ff09bf5b",
        "indicator-indigo": "#ff477ef7",
        "indicator-magenta": "#ffe248c2",
        "indicator-orange": "#fffb6514",
        "indicator-pink": "#fff63d6b",
        "indicator-yellow": "#fff7a308",
        "link-inverse": "#ff69a3fb",
        "link-primary": "#ff2c5beb",
        "link-visited": "#ff233783",
        "neutral-container-default": "#1a616366",
        "neutral-container-hover": "#33616366",
        "neutral-container-pressed": "#4d616366",
        "neutral-default": "#ff616366",
        "neutral-hover": "#ff525457",
        "neutral-on-container": "#ff616366",
        "neutral-on-grey": "#fff7f7f7",
        "neutral-pressed": "#ff444547",
        "notification-error": "#ffffe4e8",
        "notification-info": "#ffdff4fe",
        "notification-success": "#ffcffcdb",
        "notification-warning": "#fffef4c6",
        "page-background": "#ffffffff",
        "selection-control": "#ff04101e",
        "selection-control-alt": "#ff04101e",
        "support-error": "#ffe31b57",
        "support-info": "#ff05baf1",
        "support-success": "#ff009b48",
        "support-warning": "#fff7a308",
        "surface-1": "#fff7f7f7",
        "surface-2": "#ffefeff0",
        "surface-3": "#ffe4e4e5",
        "surface-inverse-accent": "#ff39424e",
        "surface-transparent": "#b3000000",
        "text-accent": "#ff04101e",
        "text-brand": "#ffdd1405",
        "text-disabled": "#ffc1c2c4",
        "text-error": "#ffe31b57",
        "text-info": "#ff0078a4",
        "text-inverse": "#fffafafa",
        "text-inverse-accent": "#fffafafb",
        "text-inverse-secondary": "#ffb0b1b3",
        "text-on-color": "#fffafafa",
        "text-on-color-disabled": "#ffa9abad",
        "text-placeholder": "#ff616366",
        "text-primary": "#ff303233",
        "text-secondary": "#ff616366",
        "text-success": "#ff007c3e",
        "text-warning": "#ffb55407",
        "toast-background": "#ff494a4d"
    }
}
